data_lab/__init__.py
data_lab/bidulgi.py
bidulgi-0.1.0.dist-info/METADATA
bidulgi-0.1.0.dist-info/WHEEL
bidulgi-0.1.0.dist-info/top_level.txt
bidulgi-0.1.0.dist-info/RECORD
