Metadata-Version: 2.1
Name: bidulgi
Version: 0.1.0
Summary: bidulgi 언어이다.
Home-page: https://github.com/5koras/bidulgi
Author: 5koras, Lump
Author-email: 5koras.business@gmail.com
License: MIT
Requires-Python: >=3.4
Requires-Dist: boto3
Requires-Dist: pymongo
